utils/__init__.py
utils/aio.py
utils/fs.py
utils/process.py
utils_core/__init__.py
utils_core/aio.py
utils_core/fs.py
utils_core/func.py
utils_core/process.py
utils_core-0.1.2.dist-info/LICENSE
utils_core-0.1.2.dist-info/METADATA
utils_core-0.1.2.dist-info/WHEEL
utils_core-0.1.2.dist-info/top_level.txt
utils_core-0.1.2.dist-info/RECORD
