Metadata-Version: 1.2
Name: utils-core
Version: 0.1.2
Summary: General utilities on top of Python standard libraries
Home-page: https://github.com/maxzheng/utils-core
Author: Max Zheng
Author-email: maxzheng.os@gmail.com
License: MIT
Keywords: general utilities for standard library
Platform: UNKNOWN
Classifier: Development Status :: 5 - Production/Stable
Classifier: Intended Audience :: Developers
Classifier: Topic :: Software Development :: Libraries :: Python Modules
Classifier: License :: OSI Approved :: MIT License
Classifier: Programming Language :: Python :: 3
Classifier: Programming Language :: Python :: 3.6
Requires-Python: >=3.6
